{
    "name": "Pinq\\Queries\\Segments\\Segment",
    "line": 12,
    "short_desc": "Base class for a query segment",
    "long_desc": "Currently here for convenient namespacing",
    "hint": null,
    "tags": {
        "author": [
            [
                "Elliot",
                "Levin",
                "<elliot@aanet.com.au>"
            ]
        ]
    },
    "namespace": "Pinq\\Queries\\Segments",
    "file": "C:\\Program Files\\Apache Software Foundation\\Apache2.4\\htdocs\\PinqSite\\_layouts\\api\/pinq\/Source\\Queries\\Segments\\Segment.php",
    "hash": "ad4ca26e11a6e9d6c8ab7c2da9a8fa8950fe2e52",
    "parent": null,
    "modifiers": 16,
    "is_trait": false,
    "is_interface": false,
    "aliases": [

    ],
    "errors": [

    ],
    "interfaces": {
        "Pinq\\Queries\\ISegment": "Pinq\\Queries\\ISegment"
    },
    "properties": [

    ],
    "methods": [

    ],
    "constants": [

    ]
}