{
    "name": "Pinq\\Queries\\Segments\\EqualityJoin",
    "line": 13,
    "short_desc": "Query segment for an equality join base on a key select for the outer values an another for the inner values",
    "long_desc": "",
    "hint": null,
    "tags": {
        "author": [
            [
                "Elliot",
                "Levin",
                "<elliot@aanet.com.au>"
            ]
        ]
    },
    "namespace": "Pinq\\Queries\\Segments",
    "file": "C:\\Program Files\\Apache Software Foundation\\Apache2.4\\htdocs\\PinqSite\\_layouts\\api\/pinq\/Source\\Queries\\Segments\\EqualityJoin.php",
    "hash": "288b2cadab4377d802f78f71d679ae5096946552",
    "parent": "Pinq\\Queries\\Segments\\JoinBase",
    "modifiers": 0,
    "is_trait": false,
    "is_interface": false,
    "aliases": {
        "FunctionExpressionTree": "Pinq\\FunctionExpressionTree"
    },
    "errors": [

    ],
    "interfaces": [

    ],
    "properties": [

    ],
    "methods": {
        "__construct": {
            "name": "__construct",
            "line": 29,
            "short_desc": "",
            "long_desc": "",
            "hint": null,
            "hint_desc": null,
            "tags": [

            ],
            "modifiers": "1",
            "is_by_ref": "",
            "exceptions": [

            ],
            "errors": [

            ],
            "parameters": {
                "values": {
                    "name": "values",
                    "line": 29,
                    "short_desc": null,
                    "long_desc": null,
                    "hint": null,
                    "tags": [

                    ],
                    "modifiers": "",
                    "default": null,
                    "is_by_ref": false
                },
                "isGroupJoin": {
                    "name": "isGroupJoin",
                    "line": 29,
                    "short_desc": null,
                    "long_desc": null,
                    "hint": null,
                    "tags": [

                    ],
                    "modifiers": "",
                    "default": null,
                    "is_by_ref": false
                },
                "outerKeyFunction": {
                    "name": "outerKeyFunction",
                    "line": 29,
                    "short_desc": null,
                    "long_desc": null,
                    "hint": [
                        [
                            "Pinq\\FunctionExpressionTree",
                            false
                        ]
                    ],
                    "tags": [

                    ],
                    "modifiers": "FunctionExpressionTree",
                    "default": null,
                    "is_by_ref": false
                },
                "innerKeyFunction": {
                    "name": "innerKeyFunction",
                    "line": 29,
                    "short_desc": null,
                    "long_desc": null,
                    "hint": [
                        [
                            "Pinq\\FunctionExpressionTree",
                            false
                        ]
                    ],
                    "tags": [

                    ],
                    "modifiers": "FunctionExpressionTree",
                    "default": null,
                    "is_by_ref": false
                },
                "joiningFunction": {
                    "name": "joiningFunction",
                    "line": 29,
                    "short_desc": null,
                    "long_desc": null,
                    "hint": [
                        [
                            "Pinq\\FunctionExpressionTree",
                            false
                        ]
                    ],
                    "tags": [

                    ],
                    "modifiers": "FunctionExpressionTree",
                    "default": null,
                    "is_by_ref": false
                }
            }
        },
        "getType": {
            "name": "getType",
            "line": 36,
            "short_desc": "",
            "long_desc": "",
            "hint": [
                [
                    "int",
                    false
                ]
            ],
            "hint_desc": "The query type",
            "tags": [

            ],
            "modifiers": "1",
            "is_by_ref": "",
            "exceptions": [

            ],
            "errors": [

            ],
            "parameters": [

            ]
        },
        "traverse": {
            "name": "traverse",
            "line": 41,
            "short_desc": "",
            "long_desc": "",
            "hint": [
                [
                    "Pinq\\Queries\\ISegment",
                    false
                ]
            ],
            "hint_desc": "",
            "tags": [

            ],
            "modifiers": "1",
            "is_by_ref": "",
            "exceptions": [

            ],
            "errors": [

            ],
            "parameters": {
                "walker": {
                    "name": "walker",
                    "line": 41,
                    "short_desc": null,
                    "long_desc": null,
                    "hint": [
                        [
                            "Pinq\\Queries\\Segments\\SegmentWalker",
                            false
                        ]
                    ],
                    "tags": [

                    ],
                    "modifiers": "SegmentWalker",
                    "default": null,
                    "is_by_ref": false
                }
            }
        },
        "getOuterKeyFunctionExpressionTree": {
            "name": "getOuterKeyFunctionExpressionTree",
            "line": 49,
            "short_desc": "",
            "long_desc": "",
            "hint": [
                [
                    "Pinq\\FunctionExpressionTree",
                    false
                ]
            ],
            "hint_desc": "",
            "tags": [

            ],
            "modifiers": "1",
            "is_by_ref": "",
            "exceptions": [

            ],
            "errors": [

            ],
            "parameters": [

            ]
        },
        "getInnerKeyFunctionExpressionTree": {
            "name": "getInnerKeyFunctionExpressionTree",
            "line": 57,
            "short_desc": "",
            "long_desc": "",
            "hint": [
                [
                    "Pinq\\FunctionExpressionTree",
                    false
                ]
            ],
            "hint_desc": "",
            "tags": [

            ],
            "modifiers": "1",
            "is_by_ref": "",
            "exceptions": [

            ],
            "errors": [

            ],
            "parameters": [

            ]
        },
        "update": {
            "name": "update",
            "line": 62,
            "short_desc": "",
            "long_desc": "",
            "hint": null,
            "hint_desc": null,
            "tags": [

            ],
            "modifiers": "1",
            "is_by_ref": "",
            "exceptions": [

            ],
            "errors": [

            ],
            "parameters": {
                "values": {
                    "name": "values",
                    "line": 62,
                    "short_desc": null,
                    "long_desc": null,
                    "hint": null,
                    "tags": [

                    ],
                    "modifiers": "",
                    "default": null,
                    "is_by_ref": false
                },
                "isGroupJoin": {
                    "name": "isGroupJoin",
                    "line": 62,
                    "short_desc": null,
                    "long_desc": null,
                    "hint": null,
                    "tags": [

                    ],
                    "modifiers": "",
                    "default": null,
                    "is_by_ref": false
                },
                "outerKeyFunction": {
                    "name": "outerKeyFunction",
                    "line": 62,
                    "short_desc": null,
                    "long_desc": null,
                    "hint": [
                        [
                            "Pinq\\FunctionExpressionTree",
                            false
                        ]
                    ],
                    "tags": [

                    ],
                    "modifiers": "FunctionExpressionTree",
                    "default": null,
                    "is_by_ref": false
                },
                "innerKeyFunction": {
                    "name": "innerKeyFunction",
                    "line": 62,
                    "short_desc": null,
                    "long_desc": null,
                    "hint": [
                        [
                            "Pinq\\FunctionExpressionTree",
                            false
                        ]
                    ],
                    "tags": [

                    ],
                    "modifiers": "FunctionExpressionTree",
                    "default": null,
                    "is_by_ref": false
                },
                "joiningFunction": {
                    "name": "joiningFunction",
                    "line": 62,
                    "short_desc": null,
                    "long_desc": null,
                    "hint": [
                        [
                            "Pinq\\FunctionExpressionTree",
                            false
                        ]
                    ],
                    "tags": [

                    ],
                    "modifiers": "FunctionExpressionTree",
                    "default": null,
                    "is_by_ref": false
                }
            }
        }
    },
    "constants": [

    ]
}