{
    "name": "Pinq\\Providers\\Caching\\RequestEvaluator",
    "line": 15,
    "short_desc": "A caching request evaluator instance, the inner evaluators results will be cached and reused if an equivalent request is called again.",
    "long_desc": "",
    "hint": null,
    "tags": {
        "author": [
            [
                "Elliot",
                "Levin",
                "<elliot@aanet.com.au>"
            ]
        ]
    },
    "namespace": "Pinq\\Providers\\Caching",
    "file": "C:\\Program Files\\Apache Software Foundation\\Apache2.4\\htdocs\\PinqSite\\_layouts\\api\/pinq\/Source\\Providers\\Caching\\RequestEvaluator.php",
    "hash": "24c071684f4c6fe10824a644b21ca55e6c342f5b",
    "parent": "Pinq\\Queries\\Requests\\RequestVisitor",
    "modifiers": 0,
    "is_trait": false,
    "is_interface": false,
    "aliases": {
        "Queries": "Pinq\\Queries",
        "Requests": "Pinq\\Queries\\Requests"
    },
    "errors": [

    ],
    "interfaces": [

    ],
    "properties": [

    ],
    "methods": {
        "__construct": {
            "name": "__construct",
            "line": 27,
            "short_desc": "",
            "long_desc": "",
            "hint": null,
            "hint_desc": null,
            "tags": [

            ],
            "modifiers": "1",
            "is_by_ref": "",
            "exceptions": [

            ],
            "errors": [

            ],
            "parameters": {
                "innerRequestEvaluator": {
                    "name": "innerRequestEvaluator",
                    "line": 27,
                    "short_desc": null,
                    "long_desc": null,
                    "hint": [
                        [
                            "Pinq\\Providers\\Caching\\Requests\\RequestVisitor",
                            false
                        ]
                    ],
                    "tags": [

                    ],
                    "modifiers": "Requests\\RequestVisitor",
                    "default": null,
                    "is_by_ref": false
                }
            }
        },
        "visitValues": {
            "name": "visitValues",
            "line": 43,
            "short_desc": "",
            "long_desc": "",
            "hint": null,
            "hint_desc": null,
            "tags": [

            ],
            "modifiers": "1",
            "is_by_ref": "",
            "exceptions": [

            ],
            "errors": [

            ],
            "parameters": {
                "request": {
                    "name": "request",
                    "line": 43,
                    "short_desc": null,
                    "long_desc": null,
                    "hint": [
                        [
                            "Pinq\\Providers\\Caching\\Requests\\Values",
                            false
                        ]
                    ],
                    "tags": [

                    ],
                    "modifiers": "Requests\\Values",
                    "default": null,
                    "is_by_ref": false
                }
            }
        },
        "visitCount": {
            "name": "visitCount",
            "line": 48,
            "short_desc": "",
            "long_desc": "",
            "hint": null,
            "hint_desc": null,
            "tags": [

            ],
            "modifiers": "1",
            "is_by_ref": "",
            "exceptions": [

            ],
            "errors": [

            ],
            "parameters": {
                "request": {
                    "name": "request",
                    "line": 48,
                    "short_desc": null,
                    "long_desc": null,
                    "hint": [
                        [
                            "Pinq\\Providers\\Caching\\Requests\\Count",
                            false
                        ]
                    ],
                    "tags": [

                    ],
                    "modifiers": "Requests\\Count",
                    "default": null,
                    "is_by_ref": false
                }
            }
        },
        "visitExists": {
            "name": "visitExists",
            "line": 53,
            "short_desc": "",
            "long_desc": "",
            "hint": null,
            "hint_desc": null,
            "tags": [

            ],
            "modifiers": "1",
            "is_by_ref": "",
            "exceptions": [

            ],
            "errors": [

            ],
            "parameters": {
                "request": {
                    "name": "request",
                    "line": 53,
                    "short_desc": null,
                    "long_desc": null,
                    "hint": [
                        [
                            "Pinq\\Providers\\Caching\\Requests\\Exists",
                            false
                        ]
                    ],
                    "tags": [

                    ],
                    "modifiers": "Requests\\Exists",
                    "default": null,
                    "is_by_ref": false
                }
            }
        },
        "visitFirst": {
            "name": "visitFirst",
            "line": 58,
            "short_desc": "",
            "long_desc": "",
            "hint": null,
            "hint_desc": null,
            "tags": [

            ],
            "modifiers": "1",
            "is_by_ref": "",
            "exceptions": [

            ],
            "errors": [

            ],
            "parameters": {
                "request": {
                    "name": "request",
                    "line": 58,
                    "short_desc": null,
                    "long_desc": null,
                    "hint": [
                        [
                            "Pinq\\Providers\\Caching\\Requests\\First",
                            false
                        ]
                    ],
                    "tags": [

                    ],
                    "modifiers": "Requests\\First",
                    "default": null,
                    "is_by_ref": false
                }
            }
        },
        "visitLast": {
            "name": "visitLast",
            "line": 63,
            "short_desc": "",
            "long_desc": "",
            "hint": null,
            "hint_desc": null,
            "tags": [

            ],
            "modifiers": "1",
            "is_by_ref": "",
            "exceptions": [

            ],
            "errors": [

            ],
            "parameters": {
                "request": {
                    "name": "request",
                    "line": 63,
                    "short_desc": null,
                    "long_desc": null,
                    "hint": [
                        [
                            "Pinq\\Providers\\Caching\\Requests\\Last",
                            false
                        ]
                    ],
                    "tags": [

                    ],
                    "modifiers": "Requests\\Last",
                    "default": null,
                    "is_by_ref": false
                }
            }
        },
        "visitContains": {
            "name": "visitContains",
            "line": 68,
            "short_desc": "",
            "long_desc": "",
            "hint": null,
            "hint_desc": null,
            "tags": [

            ],
            "modifiers": "1",
            "is_by_ref": "",
            "exceptions": [

            ],
            "errors": [

            ],
            "parameters": {
                "request": {
                    "name": "request",
                    "line": 68,
                    "short_desc": null,
                    "long_desc": null,
                    "hint": [
                        [
                            "Pinq\\Providers\\Caching\\Requests\\Contains",
                            false
                        ]
                    ],
                    "tags": [

                    ],
                    "modifiers": "Requests\\Contains",
                    "default": null,
                    "is_by_ref": false
                }
            }
        },
        "visitGetIndex": {
            "name": "visitGetIndex",
            "line": 73,
            "short_desc": "",
            "long_desc": "",
            "hint": null,
            "hint_desc": null,
            "tags": [

            ],
            "modifiers": "1",
            "is_by_ref": "",
            "exceptions": [

            ],
            "errors": [

            ],
            "parameters": {
                "request": {
                    "name": "request",
                    "line": 73,
                    "short_desc": null,
                    "long_desc": null,
                    "hint": [
                        [
                            "Pinq\\Providers\\Caching\\Requests\\GetIndex",
                            false
                        ]
                    ],
                    "tags": [

                    ],
                    "modifiers": "Requests\\GetIndex",
                    "default": null,
                    "is_by_ref": false
                }
            }
        },
        "visitIssetIndex": {
            "name": "visitIssetIndex",
            "line": 78,
            "short_desc": "",
            "long_desc": "",
            "hint": null,
            "hint_desc": null,
            "tags": [

            ],
            "modifiers": "1",
            "is_by_ref": "",
            "exceptions": [

            ],
            "errors": [

            ],
            "parameters": {
                "request": {
                    "name": "request",
                    "line": 78,
                    "short_desc": null,
                    "long_desc": null,
                    "hint": [
                        [
                            "Pinq\\Providers\\Caching\\Requests\\IssetIndex",
                            false
                        ]
                    ],
                    "tags": [

                    ],
                    "modifiers": "Requests\\IssetIndex",
                    "default": null,
                    "is_by_ref": false
                }
            }
        },
        "visitAggregate": {
            "name": "visitAggregate",
            "line": 83,
            "short_desc": "",
            "long_desc": "",
            "hint": null,
            "hint_desc": null,
            "tags": [

            ],
            "modifiers": "1",
            "is_by_ref": "",
            "exceptions": [

            ],
            "errors": [

            ],
            "parameters": {
                "request": {
                    "name": "request",
                    "line": 83,
                    "short_desc": null,
                    "long_desc": null,
                    "hint": [
                        [
                            "Pinq\\Providers\\Caching\\Requests\\Aggregate",
                            false
                        ]
                    ],
                    "tags": [

                    ],
                    "modifiers": "Requests\\Aggregate",
                    "default": null,
                    "is_by_ref": false
                }
            }
        },
        "visitMaximum": {
            "name": "visitMaximum",
            "line": 88,
            "short_desc": "",
            "long_desc": "",
            "hint": null,
            "hint_desc": null,
            "tags": [

            ],
            "modifiers": "1",
            "is_by_ref": "",
            "exceptions": [

            ],
            "errors": [

            ],
            "parameters": {
                "request": {
                    "name": "request",
                    "line": 88,
                    "short_desc": null,
                    "long_desc": null,
                    "hint": [
                        [
                            "Pinq\\Providers\\Caching\\Requests\\Maximum",
                            false
                        ]
                    ],
                    "tags": [

                    ],
                    "modifiers": "Requests\\Maximum",
                    "default": null,
                    "is_by_ref": false
                }
            }
        },
        "visitMinimum": {
            "name": "visitMinimum",
            "line": 93,
            "short_desc": "",
            "long_desc": "",
            "hint": null,
            "hint_desc": null,
            "tags": [

            ],
            "modifiers": "1",
            "is_by_ref": "",
            "exceptions": [

            ],
            "errors": [

            ],
            "parameters": {
                "request": {
                    "name": "request",
                    "line": 93,
                    "short_desc": null,
                    "long_desc": null,
                    "hint": [
                        [
                            "Pinq\\Providers\\Caching\\Requests\\Minimum",
                            false
                        ]
                    ],
                    "tags": [

                    ],
                    "modifiers": "Requests\\Minimum",
                    "default": null,
                    "is_by_ref": false
                }
            }
        },
        "visitSum": {
            "name": "visitSum",
            "line": 98,
            "short_desc": "",
            "long_desc": "",
            "hint": null,
            "hint_desc": null,
            "tags": [

            ],
            "modifiers": "1",
            "is_by_ref": "",
            "exceptions": [

            ],
            "errors": [

            ],
            "parameters": {
                "request": {
                    "name": "request",
                    "line": 98,
                    "short_desc": null,
                    "long_desc": null,
                    "hint": [
                        [
                            "Pinq\\Providers\\Caching\\Requests\\Sum",
                            false
                        ]
                    ],
                    "tags": [

                    ],
                    "modifiers": "Requests\\Sum",
                    "default": null,
                    "is_by_ref": false
                }
            }
        },
        "visitAverage": {
            "name": "visitAverage",
            "line": 103,
            "short_desc": "",
            "long_desc": "",
            "hint": null,
            "hint_desc": null,
            "tags": [

            ],
            "modifiers": "1",
            "is_by_ref": "",
            "exceptions": [

            ],
            "errors": [

            ],
            "parameters": {
                "request": {
                    "name": "request",
                    "line": 103,
                    "short_desc": null,
                    "long_desc": null,
                    "hint": [
                        [
                            "Pinq\\Providers\\Caching\\Requests\\Average",
                            false
                        ]
                    ],
                    "tags": [

                    ],
                    "modifiers": "Requests\\Average",
                    "default": null,
                    "is_by_ref": false
                }
            }
        },
        "visitAll": {
            "name": "visitAll",
            "line": 108,
            "short_desc": "",
            "long_desc": "",
            "hint": null,
            "hint_desc": null,
            "tags": [

            ],
            "modifiers": "1",
            "is_by_ref": "",
            "exceptions": [

            ],
            "errors": [

            ],
            "parameters": {
                "request": {
                    "name": "request",
                    "line": 108,
                    "short_desc": null,
                    "long_desc": null,
                    "hint": [
                        [
                            "Pinq\\Providers\\Caching\\Requests\\All",
                            false
                        ]
                    ],
                    "tags": [

                    ],
                    "modifiers": "Requests\\All",
                    "default": null,
                    "is_by_ref": false
                }
            }
        },
        "visitAny": {
            "name": "visitAny",
            "line": 113,
            "short_desc": "",
            "long_desc": "",
            "hint": null,
            "hint_desc": null,
            "tags": [

            ],
            "modifiers": "1",
            "is_by_ref": "",
            "exceptions": [

            ],
            "errors": [

            ],
            "parameters": {
                "request": {
                    "name": "request",
                    "line": 113,
                    "short_desc": null,
                    "long_desc": null,
                    "hint": [
                        [
                            "Pinq\\Providers\\Caching\\Requests\\Any",
                            false
                        ]
                    ],
                    "tags": [

                    ],
                    "modifiers": "Requests\\Any",
                    "default": null,
                    "is_by_ref": false
                }
            }
        },
        "visitImplode": {
            "name": "visitImplode",
            "line": 118,
            "short_desc": "",
            "long_desc": "",
            "hint": null,
            "hint_desc": null,
            "tags": [

            ],
            "modifiers": "1",
            "is_by_ref": "",
            "exceptions": [

            ],
            "errors": [

            ],
            "parameters": {
                "request": {
                    "name": "request",
                    "line": 118,
                    "short_desc": null,
                    "long_desc": null,
                    "hint": [
                        [
                            "Pinq\\Providers\\Caching\\Requests\\Implode",
                            false
                        ]
                    ],
                    "tags": [

                    ],
                    "modifiers": "Requests\\Implode",
                    "default": null,
                    "is_by_ref": false
                }
            }
        }
    },
    "constants": [

    ]
}